odoo10_addon_account_banking_sepa_direct_debit-10.0.1.1.3-nspkg.pth
odoo/addons/account_banking_sepa_direct_debit/README.rst
odoo/addons/account_banking_sepa_direct_debit/__init__.py
odoo/addons/account_banking_sepa_direct_debit/__manifest__.py
odoo/addons/account_banking_sepa_direct_debit/post_install.py
odoo/addons/account_banking_sepa_direct_debit/data/account_payment_method.xml
odoo/addons/account_banking_sepa_direct_debit/data/mandate_expire_cron.xml
odoo/addons/account_banking_sepa_direct_debit/data/pain.008.001.02.xsd
odoo/addons/account_banking_sepa_direct_debit/data/pain.008.001.03.xsd
odoo/addons/account_banking_sepa_direct_debit/data/pain.008.001.04.xsd
odoo/addons/account_banking_sepa_direct_debit/data/pain.008.003.02.xsd
odoo/addons/account_banking_sepa_direct_debit/data/report_paperformat.xml
odoo/addons/account_banking_sepa_direct_debit/demo/sepa_direct_debit_demo.xml
odoo/addons/account_banking_sepa_direct_debit/i18n/account_banking_sepa_direct_debit.pot
odoo/addons/account_banking_sepa_direct_debit/i18n/da_DK.po
odoo/addons/account_banking_sepa_direct_debit/i18n/de.po
odoo/addons/account_banking_sepa_direct_debit/i18n/es.po
odoo/addons/account_banking_sepa_direct_debit/i18n/fr.po
odoo/addons/account_banking_sepa_direct_debit/i18n/hr.po
odoo/addons/account_banking_sepa_direct_debit/i18n/nb_NO.po
odoo/addons/account_banking_sepa_direct_debit/i18n/nl.po
odoo/addons/account_banking_sepa_direct_debit/i18n/nl_NL.po
odoo/addons/account_banking_sepa_direct_debit/i18n/pt.po
odoo/addons/account_banking_sepa_direct_debit/i18n/pt_BR.po
odoo/addons/account_banking_sepa_direct_debit/i18n/sl.po
odoo/addons/account_banking_sepa_direct_debit/models/__init__.py
odoo/addons/account_banking_sepa_direct_debit/models/account_banking_mandate.py
odoo/addons/account_banking_sepa_direct_debit/models/account_payment_method.py
odoo/addons/account_banking_sepa_direct_debit/models/account_payment_mode.py
odoo10_addon_account_banking_sepa_direct_debit-10.0.1.1.3.dist-info/METADATA
odoo10_addon_account_banking_sepa_direct_debit-10.0.1.1.3.dist-info/WHEEL
odoo10_addon_account_banking_sepa_direct_debit-10.0.1.1.3.dist-info/namespace_packages.txt
odoo10_addon_account_banking_sepa_direct_debit-10.0.1.1.3.dist-info/top_level.txt
odoo10_addon_account_banking_sepa_direct_debit-10.0.1.1.3.dist-info/RECORD
