Metadata-Version: 2.1
Name: odoo10-addon-account-banking-sepa-direct-debit
Version: 10.0.1.1.3
Summary: Create SEPA files for Direct Debit
Home-page: https://github.com/OCA/bank-payment
Author: Akretion, Tecnativa, Odoo Community Association (OCA)
Author-email: support@odoo-community.org
License: AGPL-3
Platform: UNKNOWN
Classifier: Programming Language :: Python
Classifier: Framework :: Odoo
Classifier: License :: OSI Approved :: GNU Affero General Public License v3
Requires-Python: ~=2.7
Requires-Dist: odoo10-addon-account-banking-mandate
Requires-Dist: odoo10-addon-account-banking-pain-base
Requires-Dist: odoo (<10.1dev,>=10.0)
